simplecnn
