Metadata-Version: 1.0
Name: SimpleCNN
Version: 4.0
Summary: SimpleCNN
Home-page: UNKNOWN
Author: Zhengxing Chen
Author-email: czxttkl@gmail.com
License: UNKNOWN
Platform: UNKNOWN
